opthub_api_client/__init__.py
opthub_api_client/api/__init__.py
opthub_api_client/api/match_trials_api.py
opthub_api_client/api_client.py
opthub_api_client/api_response.py
opthub_api_client/configuration.py
opthub_api_client/exceptions.py
opthub_api_client/models/__init__.py
opthub_api_client/models/auth_error_code.py
opthub_api_client/models/auth_error_response.py
opthub_api_client/models/create_match_trial400_response.py
opthub_api_client/models/create_match_trial403_response.py
opthub_api_client/models/create_match_trial404_response.py
opthub_api_client/models/create_match_trial_request.py
opthub_api_client/models/get_match_evaluation404_response.py
opthub_api_client/models/get_match_score404_response.py
opthub_api_client/models/get_match_trial403_response.py
opthub_api_client/models/get_match_trial404_response.py
opthub_api_client/models/get_solution404_response.py
opthub_api_client/models/match_trial_evaluation.py
opthub_api_client/models/match_trial_response.py
opthub_api_client/models/match_trial_score.py
opthub_api_client/models/match_trial_status.py
opthub_api_client/models/runner_status.py
opthub_api_client/models/scalar_or_vector.py
opthub_api_client/models/server_error_code.py
opthub_api_client/models/server_error_response.py
opthub_api_client/models/solution.py
opthub_api_client/py.typed
opthub_api_client/rest.py
opthub_api_client-1.0.0.dist-info/LICENSE
opthub_api_client-1.0.0.dist-info/METADATA
opthub_api_client-1.0.0.dist-info/WHEEL
opthub_api_client-1.0.0.dist-info/RECORD
