Metadata-Version: 2.1
Name: opthub_api_client
Version: 1.0.0
Summary: OptHub REST API
Home-page: https://github.com/opthub-org/opthub-api-client-python
License: MIT
Keywords: OpenAPI,OpenAPI-Generator,OptHub REST API
Author: OpenAPI Generator Community
Author-email: dev@opthub.ai
Requires-Python: >=3.7,<4.0
Classifier: License :: OSI Approved :: MIT License
Classifier: Programming Language :: Python :: 3
Classifier: Programming Language :: Python :: 3.7
Classifier: Programming Language :: Python :: 3.8
Classifier: Programming Language :: Python :: 3.9
Classifier: Programming Language :: Python :: 3.10
Classifier: Programming Language :: Python :: 3.11
Classifier: Programming Language :: Python :: 3.12
Requires-Dist: pydantic (>=2)
Requires-Dist: python-dateutil (>=2.8.2)
Requires-Dist: typing-extensions (>=4.7.1)
Requires-Dist: urllib3 (>=1.25.3)
Project-URL: Repository, https://github.com/opthub-org/opthub-api-client-python
